<?xml version='1.0' encoding='UTF-8'?>
<inventory format-version="1.0">
	<drivers>
		<driver>
			<id>c84884a3-f4e8-4316-9117-a073bac4d8eb</id>
			<name>AWS Driver 1.0.0</name>
			<description></description>
			<attachment>
				<id>7b8357e9-d848-42dc-923b-9caee5f3141f</id>
				<name>aws-driver-1.0.0</name>
				<contentType>application/zip</contentType>
			</attachment>
		</driver>
		<driver>
			<id>9b64f0e5-7724-4d90-8a78-3884b8a44230</id>
			<name>AWS L2 Switch Driver 1.0.0</name>
			<description></description>
			<attachment>
				<id>0b35bff5-2386-44d6-aba2-805ff2505325</id>
				<name>aws-l2-switch-driver-1.0.0</name>
				<contentType>application/zip</contentType>
			</attachment>
		</driver>
		<driver>
			<id>68ca4b20-96de-4c72-a1b7-61bddefc424c</id>
			<name>Calient Driver 1.0.11</name>
			<description></description>
			<attachment>
				<id>dc456424-ecf8-40a3-bf38-15ef3fd2619b</id>
				<name>calient-driver-1.0.11</name>
				<contentType>application/zip</contentType>
			</attachment>
		</driver>
		<driver>
			<id>0dafb906-4d92-47af-84a0-9e0097436f6c</id>
			<name>Cisco Driver 5.4.2</name>
			<description></description>
			<attachment>
				<id>f6e64a1e-8781-441e-a89b-580ad72bbde2</id>
				<name>cisco-driver-5.4.2</name>
				<contentType>application/zip</contentType>
			</attachment>
		</driver>
		<driver>
			<id>867c61ac-a189-11ea-bb37-0242ac130002</id>
			<name>Kubernetes Driver 1.0.0</name>
			<description></description>
			<attachment>
				<id>0b545356-3c6c-456d-a793-ffbf94a610b7</id>
				<name>kubernetes-driver-1.0.0</name>
				<contentType>application/zip</contentType>
			</attachment>
		</driver>
		<driver>
			<id>66789c02-22f2-11e9-ab1d-663bd873d93c</id>
			<name>Lepton L1 Switch Driver 2.0.0</name>
			<description></description>
			<attachment>
				<id>91de586d-dce8-49a2-807c-2767183ac45e</id>
				<name>lepton-driver-2.0.0</name>
				<contentType>application/zip</contentType>
			</attachment>
		</driver>
		<driver>
			<id>c1e3ce79-748e-4749-913d-a399c0f22b77</id>
			<name>MRV Driver 5.4.0</name>
			<description></description>
			<attachment>
				<id>379e8d7f-4b33-4634-b3d7-88514c6c0f47</id>
				<name>mrv-driver-5.4.0</name>
				<contentType>application/zip</contentType>
			</attachment>
		</driver>
		<driver>
			<id>caaf1720-d3e6-4ca1-9615-3458b80d1cf3</id>
			<name>NetScout Driver 2.5.1</name>
			<description></description>
			<attachment>
				<id>c1dda770-3e1a-47d8-8891-ac092d17f11c</id>
				<name>netscout-driver-2.5.1</name>
				<contentType>application/zip</contentType>
			</attachment>
		</driver>
		<driver>
			<id>e660edc3-e5b6-4ecd-bcd9-5a152ffb94ec</id>
			<name>Ping Driver 2.0.0</name>
			<description></description>
			<attachment>
				<id>bd4effe5-883c-4926-8c66-b4b2310d1e3a</id>
				<name>ping-driver-2.0.0</name>
				<contentType>application/zip</contentType>
			</attachment>
		</driver>
		<driver>
			<id>b7a10e22-d00f-4dc2-a3f4-f375a08cffe5</id>
			<name>Ping6 Driver 1.2.0</name>
			<description></description>
			<attachment>
				<id>d1e1b1ac-e9be-4fcd-8651-436a5777debd</id>
				<name>ping6-driver-1.2.0</name>
				<contentType>application/zip</contentType>
			</attachment>
		</driver>
		<driver>
			<id>960abfe9-d550-4d14-870a-732672f07c46</id>
			<name>Polatis Driver 6.7.2</name>
			<description></description>
			<attachment>
				<id>1cdc67eb-ce65-42f3-b432-7e9ec0ef7ea9</id>
				<name>polatis-driver-6.7.2</name>
				<contentType>application/zip</contentType>
			</attachment>
		</driver>
		<driver>
			<id>565b35cf-2764-44c7-8312-a3be6dec9997</id>
			<name>SNMP Driver 2.5.0</name>
			<description></description>
			<attachment>
				<id>cc7fc818-7da8-46bb-8b52-17ca4bfec9a3</id>
				<name>snmp-driver-2.5.0</name>
				<contentType>application/zip</contentType>
			</attachment>
		</driver>
	</drivers>
	<templates>
		<template>
			<id>0f8dec97-74fa-4ec2-9aef-c8f5894436c7</id>
			<revisionId>0f8dec97-74fa-4ec2-9aef-c8f5894436c7</revisionId>
			<name>Template1</name>
			<description></description>
			<isTemplate>true</isTemplate>
			<type>DEVICE</type>
			<interfaceType>ORCHESTRATION</interfaceType>
			<utilizationType>SHARED</utilizationType>
			<reservationTime>IMMEDIATE</reservationTime>
			<isCustomReservationTime>false</isCustomReservationTime>
			<icon/>
			<defaultImageAttach/>
			<defaultConfigAttach>
				<attachment>
					<id>946e5de8-f26b-4166-a114-55e85c6e4847</id>
					<name>c1.txt</name>
					<contentType>text/plain</contentType>
				</attachment>
			</defaultConfigAttach>
		</template>
	</templates>
	<cableTypes/>
	<resources/>
	<cables/>
	<orchestratedResources/>
	<abstractResources/>
	<links/>
	<associations/>
</inventory>